denomagic/__init__.py
denomagic/denomagic.py
denomagic-1.1.0.dist-info/METADATA
denomagic-1.1.0.dist-info/WHEEL
denomagic-1.1.0.dist-info/top_level.txt
denomagic-1.1.0.dist-info/RECORD
